{
  "id": "2c3eaf69-3264-488a-b8b3-08a44db01bf9",
  "prevId": "d3601655-a376-4a56-b615-625cdeb9575d",
  "version": "7",
  "dialect": "postgresql",
  "tables": {
    "public.users": {
      "name": "users",
      "schema": "",
      "columns": {
        "id": {
          "name": "id",
          "type": "uuid",
          "primaryKey": true,
          "notNull": true,
          "default": "gen_random_uuid()"
        },
        "firstname": {
          "name": "firstname",
          "type": "varchar(100)",
          "primaryKey": false,
          "notNull": true
        },
        "lastname": {
          "name": "lastname",
          "type": "varchar(100)",
          "primaryKey": false,
          "notNull": true
        },
        "email": {
          "name": "email",
          "type": "varchar(255)",
          "primaryKey": false,
          "notNull": true
        },
        "password": {
          "name": "password",
          "type": "varchar",
          "primaryKey": false,
          "notNull": true
        },
        "bio": {
          "name": "bio",
          "type": "varchar(255)",
          "primaryKey": false,
          "notNull": false
        },
        "picture": {
          "name": "picture",
          "type": "text",
          "primaryKey": false,
          "notNull": false,
          "default": "''"
        },
        "nativeLanguage": {
          "name": "nativeLanguage",
          "type": "varchar(25)",
          "primaryKey": false,
          "notNull": false,
          "default": "''"
        },
        "learningLanguage": {
          "name": "learningLanguage",
          "type": "varchar(25)",
          "primaryKey": false,
          "notNull": false,
          "default": "''"
        },
        "location": {
          "name": "location",
          "type": "varchar(30)",
          "primaryKey": false,
          "notNull": false,
          "default": "''"
        },
        "isOnboarded": {
          "name": "isOnboarded",
          "type": "boolean",
          "primaryKey": false,
          "notNull": true,
          "default": false
        },
        "updated_at": {
          "name": "updated_at",
          "type": "timestamp",
          "primaryKey": false,
          "notNull": false
        },
        "created_at": {
          "name": "created_at",
          "type": "timestamp",
          "primaryKey": false,
          "notNull": true,
          "default": "now()"
        },
        "deleted_at": {
          "name": "deleted_at",
          "type": "timestamp",
          "primaryKey": false,
          "notNull": false
        }
      },
      "indexes": {},
      "foreignKeys": {},
      "compositePrimaryKeys": {},
      "uniqueConstraints": {
        "users_email_unique": {
          "name": "users_email_unique",
          "nullsNotDistinct": false,
          "columns": [
            "email"
          ]
        }
      },
      "policies": {},
      "checkConstraints": {},
      "isRLSEnabled": false
    }
  },
  "enums": {},
  "schemas": {},
  "sequences": {},
  "roles": {},
  "policies": {},
  "views": {},
  "_meta": {
    "columns": {},
    "schemas": {},
    "tables": {}
  }
}